{
  "usuario": [
    {
      "id": 2,
      "nome": "Jair Ferraz",
      "email": "jairferraz@gmail.com",
      "senha": "2015288"
    },
    {
      "nome": "45",
      "email": "a@a.com",
      "senha": "dghdhdghdghhgddghdgh",
      "id": 3
    },
    {
      "nome": "henrique ",
      "email": "henrique@henrique.com",
      "senha": "henrique",
      "id": 4
    },
    {
      "nome": "henrique",
      "email": "henrique@henrique.com",
      "senha": "1234567",
      "id": 5
    },
    {
      "nome": "herique",
      "email": "henrique@henrique.com",
      "senha": "2222222222222",
      "id": 6
    }
  ],
  "categorias": [
    {
      "id": 1,
      "nome": "Front-end"
    }
  ],
  "lista": [
    {
      "id": 1,
      "nome": "Criar uma pagina front-end",
      "categoriaId": 1,
      "concluida": "false"
    }
  ],
  "tarefa": [
    {
      "id": 1,
      "listaId": 1,
      "nome": "Criar uma cabeçalho para pagina principal",
      "concluida": "true",
      "usuarioId": "1"
    }
  ]
}